tree2proj/__init__.py
tree2proj/builder.py
tree2proj/cli.py
tree2proj/example.py
tree2proj-0.1.1.dist-info/LICENSE
tree2proj-0.1.1.dist-info/METADATA
tree2proj-0.1.1.dist-info/WHEEL
tree2proj-0.1.1.dist-info/entry_points.txt
tree2proj-0.1.1.dist-info/top_level.txt
tree2proj-0.1.1.dist-info/RECORD
