Metadata-Version: 2.1
Name: tree2proj
Version: 0.1.1
Summary: Generate project folders/files from JSON tree (via tree2json)
Home-page: https://github.com/Knighthood2001/Python-tree2proj
Author: knighthood
Author-email: knighthood <2109695291@qq.com>
Requires-Python: >=3.7
License-File: LICENSE
Requires-Dist: tree2json >=0.1.3
Requires-Dist: pyperclip >=1.8.0
